fast_mu_builder/__init__.py
fast_mu_builder/attach/__init__.py
fast_mu_builder/attach/api.py
fast_mu_builder/attach/gql_controller.py
fast_mu_builder/attach/request.py
fast_mu_builder/attach/response.py
fast_mu_builder/attach/service.py
fast_mu_builder/attach/templates/__init__.py
fast_mu_builder/attach/templates/attachment_mutations.py
fast_mu_builder/attach/templates/attachment_queries.py
fast_mu_builder/attach/templates/gql_input_template.py
fast_mu_builder/attach/templates/gql_type_template.py
fast_mu_builder/attach/templates/graphql_api_template.py
fast_mu_builder/auth/__init__.py
fast_mu_builder/auth/auth.py
fast_mu_builder/auth/context.py
fast_mu_builder/auth/jwt_handler.py
fast_mu_builder/auth/middleware.py
fast_mu_builder/auth/redis.py
fast_mu_builder/auth/session_handler.py
fast_mu_builder/auth/mixings/HeadshipMixing.py
fast_mu_builder/auth/mixings/__init__.py
fast_mu_builder/commands/__init__.py
fast_mu_builder/commands/graphql.py
fast_mu_builder/common/__init__.py
fast_mu_builder/common/models.py
fast_mu_builder/common/schemas.py
fast_mu_builder/common/request/__init__.py
fast_mu_builder/common/request/schemas.py
fast_mu_builder/common/response/__init__.py
fast_mu_builder/common/response/codes.py
fast_mu_builder/common/response/schemas.py
fast_mu_builder/common/templates/module_init_.py
fast_mu_builder/common/validation/__init__.py
fast_mu_builder/common/validation/decorators.py
fast_mu_builder/common/validation/field_validator.py
fast_mu_builder/common/validation/rules.py
fast_mu_builder/crud/__init__.py
fast_mu_builder/crud/controller.py
fast_mu_builder/crud/gql_controller.py
fast_mu_builder/crud/graphql_api_gen.py
fast_mu_builder/crud/graphql_schema_gen.py
fast_mu_builder/crud/rest_api.py
fast_mu_builder/crud/templates/__init__.py
fast_mu_builder/crud/templates/controller_template.py
fast_mu_builder/crud/templates/gql_input_template.py
fast_mu_builder/crud/templates/gql_schemas_template.py
fast_mu_builder/crud/templates/gql_type_template.py
fast_mu_builder-0.1.0.12.dist-info/licenses/LICENSE
fast_mu_builder-0.1.0.12.dist-info/METADATA
fast_mu_builder-0.1.0.12.dist-info/WHEEL
fast_mu_builder-0.1.0.12.dist-info/entry_points.txt
fast_mu_builder-0.1.0.12.dist-info/top_level.txt
fast_mu_builder-0.1.0.12.dist-info/RECORD
